{
    "os": "Linux-5.4.0-110-generic-x86_64-with-debian-buster-sid",
    "python": "3.7.15",
    "heartbeatAt": "2023-01-09T20:56:07.083021",
    "startedAt": "2023-01-09T20:56:06.495599",
    "docker": null,
    "cuda": null,
    "args": [
        "--model",
        "pix2pix",
        "--is_train",
        "True",
        "--cuda",
        "True",
        "--gpu_ids",
        "0",
        "--cuda_index",
        "0",
        "--dataroot",
        "../data/JSRT",
        "--amp",
        "--loss_lambda",
        "1.0",
        "--n_epochs",
        "20",
        "--n_epochs_decay",
        "80",
        "--unet_epoch",
        "20",
        "--lr",
        "2e-5",
        "--lr_dcgan",
        "4e-5",
        "--lr_d_dcgan",
        "0",
        "--display_freq",
        "10",
        "--classes",
        "1"
    ],
    "state": "running",
    "program": "train_unet.py",
    "codePath": "train_unet.py",
    "git": {
        "remote": "https://github.com/junyanz/pytorch-CycleGAN-and-pix2pix",
        "commit": "e2c7618a2f2bf4ee012f43f96d1f62fd3c3bec89"
    },
    "email": null,
    "root": "/home/li/workspace/SS-four-stages",
    "host": "ece228-4",
    "username": "li",
    "executable": "/home/li/anaconda3/envs/semantic/bin/python",
    "cpu_count": 48,
    "cpu_count_logical": 96,
    "cpu_freq": {
        "current": 1308.7286145833339,
        "min": 1200.0,
        "max": 4000.0
    },
    "cpu_freq_per_core": [
        {
            "current": 1200.096,
            "min": 1200.0,
            "max": 4000.0
        },
        {
            "current": 1200.052,
            "min": 1200.0,
            "max": 4000.0
        },
        {
            "current": 1200.82,
            "min": 1200.0,
            "max": 4000.0
        },
        {
            "current": 1200.585,
            "min": 1200.0,
            "max": 4000.0
        },
        {
            "current": 1200.209,
            "min": 1200.0,
            "max": 4000.0
        },
        {
            "current": 1200.219,
            "min": 1200.0,
            "max": 4000.0
        },
        {
            "current": 1201.014,
            "min": 1200.0,
            "max": 4000.0
        },
        {
            "current": 1200.485,
            "min": 1200.0,
            "max": 4000.0
        },
        {
            "current": 1200.495,
            "min": 1200.0,
            "max": 4000.0
        },
        {
            "current": 1200.933,
            "min": 1200.0,
            "max": 4000.0
        },
        {
            "current": 1200.163,
            "min": 1200.0,
            "max": 4000.0
        },
        {
            "current": 1200.259,
            "min": 1200.0,
            "max": 4000.0
        },
        {
            "current": 1200.155,
            "min": 1200.0,
            "max": 4000.0
        },
        {
            "current": 1248.945,
            "min": 1200.0,
            "max": 4000.0
        },
        {
            "current": 1200.268,
            "min": 1200.0,
            "max": 4000.0
        },
        {
            "current": 1200.544,
            "min": 1200.0,
            "max": 4000.0
        },
        {
            "current": 1312.191,
            "min": 1200.0,
            "max": 4000.0
        },
        {
            "current": 1200.861,
            "min": 1200.0,
            "max": 4000.0
        },
        {
            "current": 1200.476,
            "min": 1200.0,
            "max": 4000.0
        },
        {
            "current": 1200.575,
            "min": 1200.0,
            "max": 4000.0
        },
        {
            "current": 1200.637,
            "min": 1200.0,
            "max": 4000.0
        },
        {
            "current": 1200.107,
            "min": 1200.0,
            "max": 4000.0
        },
        {
            "current": 1200.052,
            "min": 1200.0,
            "max": 4000.0
        },
        {
            "current": 2754.849,
            "min": 1200.0,
            "max": 4000.0
        },
        {
            "current": 1200.786,
            "min": 1200.0,
            "max": 4000.0
        },
        {
            "current": 1201.306,
            "min": 1200.0,
            "max": 4000.0
        },
        {
            "current": 1200.724,
            "min": 1200.0,
            "max": 4000.0
        },
        {
            "current": 1201.251,
            "min": 1200.0,
            "max": 4000.0
        },
        {
            "current": 1200.76,
            "min": 1200.0,
            "max": 4000.0
        },
        {
            "current": 1816.361,
            "min": 1200.0,
            "max": 4000.0
        },
        {
            "current": 1200.738,
            "min": 1200.0,
            "max": 4000.0
        },
        {
            "current": 1362.315,
            "min": 1200.0,
            "max": 4000.0
        },
        {
            "current": 1200.608,
            "min": 1200.0,
            "max": 4000.0
        },
        {
            "current": 1368.445,
            "min": 1200.0,
            "max": 4000.0
        },
        {
            "current": 1217.759,
            "min": 1200.0,
            "max": 4000.0
        },
        {
            "current": 2997.776,
            "min": 1200.0,
            "max": 4000.0
        },
        {
            "current": 1200.431,
            "min": 1200.0,
            "max": 4000.0
        },
        {
            "current": 1200.495,
            "min": 1200.0,
            "max": 4000.0
        },
        {
            "current": 1200.656,
            "min": 1200.0,
            "max": 4000.0
        },
        {
            "current": 1200.219,
            "min": 1200.0,
            "max": 4000.0
        },
        {
            "current": 1294.227,
            "min": 1200.0,
            "max": 4000.0
        },
        {
            "current": 1200.581,
            "min": 1200.0,
            "max": 4000.0
        },
        {
            "current": 1795.33,
            "min": 1200.0,
            "max": 4000.0
        },
        {
            "current": 1201.247,
            "min": 1200.0,
            "max": 4000.0
        },
        {
            "current": 1633.503,
            "min": 1200.0,
            "max": 4000.0
        },
        {
            "current": 1200.153,
            "min": 1200.0,
            "max": 4000.0
        },
        {
            "current": 1200.188,
            "min": 1200.0,
            "max": 4000.0
        },
        {
            "current": 2871.965,
            "min": 1200.0,
            "max": 4000.0
        },
        {
            "current": 1200.456,
            "min": 1200.0,
            "max": 4000.0
        },
        {
            "current": 1200.861,
            "min": 1200.0,
            "max": 4000.0
        },
        {
            "current": 1200.921,
            "min": 1200.0,
            "max": 4000.0
        },
        {
            "current": 1200.314,
            "min": 1200.0,
            "max": 4000.0
        },
        {
            "current": 1199.841,
            "min": 1200.0,
            "max": 4000.0
        },
        {
            "current": 1200.31,
            "min": 1200.0,
            "max": 4000.0
        },
        {
            "current": 1201.093,
            "min": 1200.0,
            "max": 4000.0
        },
        {
            "current": 1200.936,
            "min": 1200.0,
            "max": 4000.0
        },
        {
            "current": 1200.163,
            "min": 1200.0,
            "max": 4000.0
        },
        {
            "current": 1200.375,
            "min": 1200.0,
            "max": 4000.0
        },
        {
            "current": 1200.369,
            "min": 1200.0,
            "max": 4000.0
        },
        {
            "current": 1200.153,
            "min": 1200.0,
            "max": 4000.0
        },
        {
            "current": 1200.415,
            "min": 1200.0,
            "max": 4000.0
        },
        {
            "current": 1253.193,
            "min": 1200.0,
            "max": 4000.0
        },
        {
            "current": 1199.784,
            "min": 1200.0,
            "max": 4000.0
        },
        {
            "current": 1199.673,
            "min": 1200.0,
            "max": 4000.0
        },
        {
            "current": 1358.141,
            "min": 1200.0,
            "max": 4000.0
        },
        {
            "current": 1200.879,
            "min": 1200.0,
            "max": 4000.0
        },
        {
            "current": 1200.61,
            "min": 1200.0,
            "max": 4000.0
        },
        {
            "current": 1200.593,
            "min": 1200.0,
            "max": 4000.0
        },
        {
            "current": 1201.425,
            "min": 1200.0,
            "max": 4000.0
        },
        {
            "current": 1200.258,
            "min": 1200.0,
            "max": 4000.0
        },
        {
            "current": 1200.41,
            "min": 1200.0,
            "max": 4000.0
        },
        {
            "current": 1701.815,
            "min": 1200.0,
            "max": 4000.0
        },
        {
            "current": 1201.131,
            "min": 1200.0,
            "max": 4000.0
        },
        {
            "current": 1200.99,
            "min": 1200.0,
            "max": 4000.0
        },
        {
            "current": 1201.221,
            "min": 1200.0,
            "max": 4000.0
        },
        {
            "current": 1200.0,
            "min": 1200.0,
            "max": 4000.0
        },
        {
            "current": 1200.516,
            "min": 1200.0,
            "max": 4000.0
        },
        {
            "current": 1801.097,
            "min": 1200.0,
            "max": 4000.0
        },
        {
            "current": 1201.512,
            "min": 1200.0,
            "max": 4000.0
        },
        {
            "current": 1290.049,
            "min": 1200.0,
            "max": 4000.0
        },
        {
            "current": 1200.734,
            "min": 1200.0,
            "max": 4000.0
        },
        {
            "current": 1286.88,
            "min": 1200.0,
            "max": 4000.0
        },
        {
            "current": 1242.573,
            "min": 1200.0,
            "max": 4000.0
        },
        {
            "current": 2999.999,
            "min": 1200.0,
            "max": 4000.0
        },
        {
            "current": 1201.236,
            "min": 1200.0,
            "max": 4000.0
        },
        {
            "current": 1199.889,
            "min": 1200.0,
            "max": 4000.0
        },
        {
            "current": 1200.398,
            "min": 1200.0,
            "max": 4000.0
        },
        {
            "current": 1201.018,
            "min": 1200.0,
            "max": 4000.0
        },
        {
            "current": 1288.151,
            "min": 1200.0,
            "max": 4000.0
        },
        {
            "current": 1200.587,
            "min": 1200.0,
            "max": 4000.0
        },
        {
            "current": 1576.49,
            "min": 1200.0,
            "max": 4000.0
        },
        {
            "current": 1200.546,
            "min": 1200.0,
            "max": 4000.0
        },
        {
            "current": 1629.976,
            "min": 1200.0,
            "max": 4000.0
        },
        {
            "current": 1199.008,
            "min": 1200.0,
            "max": 4000.0
        },
        {
            "current": 1200.773,
            "min": 1200.0,
            "max": 4000.0
        },
        {
            "current": 2909.782,
            "min": 1200.0,
            "max": 4000.0
        }
    ],
    "disk": {
        "total": 1876.7851104736328,
        "used": 1284.9130744934082
    },
    "gpu": "NVIDIA A100-PCIE-40GB",
    "gpu_count": 2,
    "gpu_devices": [
        {
            "name": "NVIDIA A100-PCIE-40GB",
            "memory_total": 42949672960
        },
        {
            "name": "NVIDIA A100-PCIE-40GB",
            "memory_total": 42949672960
        }
    ],
    "memory": {
        "total": 251.55714416503906
    }
}
