{
    "os": "Linux-5.4.0-110-generic-x86_64-with-debian-buster-sid",
    "python": "3.7.15",
    "heartbeatAt": "2023-01-09T05:12:49.113110",
    "startedAt": "2023-01-09T05:12:47.942186",
    "docker": null,
    "cuda": null,
    "args": [
        "--model",
        "pix2pix",
        "--is_train",
        "True",
        "--cuda",
        "True",
        "--gpu_ids",
        "0",
        "--cuda_index",
        "0",
        "--dataroot",
        "../data/JSRT",
        "--amp",
        "--loss_lambda",
        "1.0",
        "--n_epochs",
        "20",
        "--n_epochs_decay",
        "80",
        "--unet_epoch",
        "20",
        "--lr",
        "2e-5",
        "--lr_dcgan",
        "4e-5",
        "--lr_d_dcgan",
        "0",
        "--display_freq",
        "10",
        "--classes",
        "1"
    ],
    "state": "running",
    "program": "train_unet.py",
    "codePath": "train_unet.py",
    "git": {
        "remote": "https://github.com/junyanz/pytorch-CycleGAN-and-pix2pix",
        "commit": "e2c7618a2f2bf4ee012f43f96d1f62fd3c3bec89"
    },
    "email": null,
    "root": "/home/li/workspace/SS-four-stages",
    "host": "ece228-4",
    "username": "li",
    "executable": "/home/li/anaconda3/envs/semantic/bin/python",
    "cpu_count": 48,
    "cpu_count_logical": 96,
    "cpu_freq": {
        "current": 1512.466885416666,
        "min": 1200.0,
        "max": 4000.0
    },
    "cpu_freq_per_core": [
        {
            "current": 2292.434,
            "min": 1200.0,
            "max": 4000.0
        },
        {
            "current": 2999.218,
            "min": 1200.0,
            "max": 4000.0
        },
        {
            "current": 1250.804,
            "min": 1200.0,
            "max": 4000.0
        },
        {
            "current": 1200.298,
            "min": 1200.0,
            "max": 4000.0
        },
        {
            "current": 1201.628,
            "min": 1200.0,
            "max": 4000.0
        },
        {
            "current": 1482.94,
            "min": 1200.0,
            "max": 4000.0
        },
        {
            "current": 1954.526,
            "min": 1200.0,
            "max": 4000.0
        },
        {
            "current": 1200.661,
            "min": 1200.0,
            "max": 4000.0
        },
        {
            "current": 1200.464,
            "min": 1200.0,
            "max": 4000.0
        },
        {
            "current": 1462.117,
            "min": 1200.0,
            "max": 4000.0
        },
        {
            "current": 2241.869,
            "min": 1200.0,
            "max": 4000.0
        },
        {
            "current": 1200.586,
            "min": 1200.0,
            "max": 4000.0
        },
        {
            "current": 1200.502,
            "min": 1200.0,
            "max": 4000.0
        },
        {
            "current": 1201.21,
            "min": 1200.0,
            "max": 4000.0
        },
        {
            "current": 1459.335,
            "min": 1200.0,
            "max": 4000.0
        },
        {
            "current": 1341.602,
            "min": 1200.0,
            "max": 4000.0
        },
        {
            "current": 1549.699,
            "min": 1200.0,
            "max": 4000.0
        },
        {
            "current": 1200.79,
            "min": 1200.0,
            "max": 4000.0
        },
        {
            "current": 1200.178,
            "min": 1200.0,
            "max": 4000.0
        },
        {
            "current": 1200.536,
            "min": 1200.0,
            "max": 4000.0
        },
        {
            "current": 1200.71,
            "min": 1200.0,
            "max": 4000.0
        },
        {
            "current": 3000.0,
            "min": 1200.0,
            "max": 4000.0
        },
        {
            "current": 2999.998,
            "min": 1200.0,
            "max": 4000.0
        },
        {
            "current": 3004.042,
            "min": 1200.0,
            "max": 4000.0
        },
        {
            "current": 3000.0,
            "min": 1200.0,
            "max": 4000.0
        },
        {
            "current": 1554.015,
            "min": 1200.0,
            "max": 4000.0
        },
        {
            "current": 1200.253,
            "min": 1200.0,
            "max": 4000.0
        },
        {
            "current": 1200.314,
            "min": 1200.0,
            "max": 4000.0
        },
        {
            "current": 1201.48,
            "min": 1200.0,
            "max": 4000.0
        },
        {
            "current": 1200.629,
            "min": 1200.0,
            "max": 4000.0
        },
        {
            "current": 1201.402,
            "min": 1200.0,
            "max": 4000.0
        },
        {
            "current": 1201.301,
            "min": 1200.0,
            "max": 4000.0
        },
        {
            "current": 1200.639,
            "min": 1200.0,
            "max": 4000.0
        },
        {
            "current": 2104.697,
            "min": 1200.0,
            "max": 4000.0
        },
        {
            "current": 1200.645,
            "min": 1200.0,
            "max": 4000.0
        },
        {
            "current": 1317.219,
            "min": 1200.0,
            "max": 4000.0
        },
        {
            "current": 1200.129,
            "min": 1200.0,
            "max": 4000.0
        },
        {
            "current": 2296.242,
            "min": 1200.0,
            "max": 4000.0
        },
        {
            "current": 1201.254,
            "min": 1200.0,
            "max": 4000.0
        },
        {
            "current": 1200.516,
            "min": 1200.0,
            "max": 4000.0
        },
        {
            "current": 1452.74,
            "min": 1200.0,
            "max": 4000.0
        },
        {
            "current": 2281.735,
            "min": 1200.0,
            "max": 4000.0
        },
        {
            "current": 1201.621,
            "min": 1200.0,
            "max": 4000.0
        },
        {
            "current": 1201.471,
            "min": 1200.0,
            "max": 4000.0
        },
        {
            "current": 1309.847,
            "min": 1200.0,
            "max": 4000.0
        },
        {
            "current": 1200.322,
            "min": 1200.0,
            "max": 4000.0
        },
        {
            "current": 1200.959,
            "min": 1200.0,
            "max": 4000.0
        },
        {
            "current": 1489.154,
            "min": 1200.0,
            "max": 4000.0
        },
        {
            "current": 1789.901,
            "min": 1200.0,
            "max": 4000.0
        },
        {
            "current": 2999.999,
            "min": 1200.0,
            "max": 4000.0
        },
        {
            "current": 1254.083,
            "min": 1200.0,
            "max": 4000.0
        },
        {
            "current": 1201.201,
            "min": 1200.0,
            "max": 4000.0
        },
        {
            "current": 1201.122,
            "min": 1200.0,
            "max": 4000.0
        },
        {
            "current": 1656.57,
            "min": 1200.0,
            "max": 4000.0
        },
        {
            "current": 1558.197,
            "min": 1200.0,
            "max": 4000.0
        },
        {
            "current": 1200.309,
            "min": 1200.0,
            "max": 4000.0
        },
        {
            "current": 1201.212,
            "min": 1200.0,
            "max": 4000.0
        },
        {
            "current": 1646.946,
            "min": 1200.0,
            "max": 4000.0
        },
        {
            "current": 2262.084,
            "min": 1200.0,
            "max": 4000.0
        },
        {
            "current": 1200.078,
            "min": 1200.0,
            "max": 4000.0
        },
        {
            "current": 1199.707,
            "min": 1200.0,
            "max": 4000.0
        },
        {
            "current": 1200.228,
            "min": 1200.0,
            "max": 4000.0
        },
        {
            "current": 1613.818,
            "min": 1200.0,
            "max": 4000.0
        },
        {
            "current": 1550.214,
            "min": 1200.0,
            "max": 4000.0
        },
        {
            "current": 1421.494,
            "min": 1200.0,
            "max": 4000.0
        },
        {
            "current": 1201.052,
            "min": 1200.0,
            "max": 4000.0
        },
        {
            "current": 1201.505,
            "min": 1200.0,
            "max": 4000.0
        },
        {
            "current": 1200.551,
            "min": 1200.0,
            "max": 4000.0
        },
        {
            "current": 1200.408,
            "min": 1200.0,
            "max": 4000.0
        },
        {
            "current": 3000.844,
            "min": 1200.0,
            "max": 4000.0
        },
        {
            "current": 3003.397,
            "min": 1200.0,
            "max": 4000.0
        },
        {
            "current": 3000.0,
            "min": 1200.0,
            "max": 4000.0
        },
        {
            "current": 3001.099,
            "min": 1200.0,
            "max": 4000.0
        },
        {
            "current": 1560.098,
            "min": 1200.0,
            "max": 4000.0
        },
        {
            "current": 1200.972,
            "min": 1200.0,
            "max": 4000.0
        },
        {
            "current": 1200.388,
            "min": 1200.0,
            "max": 4000.0
        },
        {
            "current": 1200.778,
            "min": 1200.0,
            "max": 4000.0
        },
        {
            "current": 1201.591,
            "min": 1200.0,
            "max": 4000.0
        },
        {
            "current": 1200.442,
            "min": 1200.0,
            "max": 4000.0
        },
        {
            "current": 1199.81,
            "min": 1200.0,
            "max": 4000.0
        },
        {
            "current": 1200.064,
            "min": 1200.0,
            "max": 4000.0
        },
        {
            "current": 3000.0,
            "min": 1200.0,
            "max": 4000.0
        },
        {
            "current": 1200.903,
            "min": 1200.0,
            "max": 4000.0
        },
        {
            "current": 1383.037,
            "min": 1200.0,
            "max": 4000.0
        },
        {
            "current": 1200.0,
            "min": 1200.0,
            "max": 4000.0
        },
        {
            "current": 2321.921,
            "min": 1200.0,
            "max": 4000.0
        },
        {
            "current": 1200.931,
            "min": 1200.0,
            "max": 4000.0
        },
        {
            "current": 1200.772,
            "min": 1200.0,
            "max": 4000.0
        },
        {
            "current": 1459.274,
            "min": 1200.0,
            "max": 4000.0
        },
        {
            "current": 1881.65,
            "min": 1200.0,
            "max": 4000.0
        },
        {
            "current": 1201.766,
            "min": 1200.0,
            "max": 4000.0
        },
        {
            "current": 1200.57,
            "min": 1200.0,
            "max": 4000.0
        },
        {
            "current": 1364.307,
            "min": 1200.0,
            "max": 4000.0
        },
        {
            "current": 1200.759,
            "min": 1200.0,
            "max": 4000.0
        },
        {
            "current": 1201.194,
            "min": 1200.0,
            "max": 4000.0
        },
        {
            "current": 1485.942,
            "min": 1200.0,
            "max": 4000.0
        }
    ],
    "disk": {
        "total": 1876.7851104736328,
        "used": 1290.2637481689453
    },
    "gpu": "NVIDIA A100-PCIE-40GB",
    "gpu_count": 2,
    "gpu_devices": [
        {
            "name": "NVIDIA A100-PCIE-40GB",
            "memory_total": 42949672960
        },
        {
            "name": "NVIDIA A100-PCIE-40GB",
            "memory_total": 42949672960
        }
    ],
    "memory": {
        "total": 251.55714416503906
    }
}
